django_pyscss/__init__.py
django_pyscss/compiler.py
django_pyscss/compressor.py
django_pyscss/utils.py
django_pyscss/extension/__init__.py
django_pyscss/extension/django.py
django_pyscss2-3.0.0.dist-info/LICENSE
django_pyscss2-3.0.0.dist-info/METADATA
django_pyscss2-3.0.0.dist-info/WHEEL
django_pyscss2-3.0.0.dist-info/top_level.txt
django_pyscss2-3.0.0.dist-info/RECORD
