Metadata-Version: 2.1
Name: django-pyscss2
Version: 3.0.0
Summary: Makes it easier to use PySCSS in Django.
Home-page: https://github.com/e0ne/django-pyscss
Author: Ivan Kolodyazhny
Author-email: e0ne@e0ne.info
License: UNKNOWN
Keywords: django css scss sass pyscss compressor
Platform: UNKNOWN
Classifier: Development Status :: 4 - Beta
Classifier: Framework :: Django
Classifier: Intended Audience :: Developers
Classifier: License :: OSI Approved :: BSD License
Classifier: Topic :: Internet :: WWW/HTTP
Classifier: Programming Language :: Python
Classifier: Programming Language :: Python :: 2.6
Classifier: Programming Language :: Python :: 2.7
Classifier: Programming Language :: Python :: 3.3
Classifier: Programming Language :: Python :: 3.4
Requires-Dist: Django (>=1.4)
Requires-Dist: pyScss2
